{
    "0": {
        "year": 2009,
        "VAI": 5908,
        "NAI": 10989,
        "OAI": 701
    },
    "1": {
        "year": 2010,
        "VAI": 7569,
        "NAI": 13064,
        "OAI": 884
    },
    "2": {
        "year": 2011,
        "VAI": 8727,
        "NAI": 15590,
        "OAI": 1172
    },
    "3": {
        "year": 2012,
        "VAI": 7948,
        "NAI": 15690,
        "OAI": 1136
    },
    "4": {
        "year": 2013,
        "VAI": 6654,
        "NAI": 13771,
        "OAI": 1136
    },
    "5": {
        "year": 2014,
        "VAI": 6756,
        "NAI": 12693,
        "OAI": 993
    },
    "6": {
        "year": 2015,
        "VAI": 6646,
        "NAI": 12789,
        "OAI": 1011
    },
    "7": {
        "year": 2016,
        "VAI": 6459,
        "NAI": 13515,
        "OAI": 754
    }
}